oidfed_collector/__init__.py
oidfed_collector/__main__.py
oidfed_collector/_version.py
oidfed_collector/api.py
oidfed_collector/cache.py
oidfed_collector/collection.py
oidfed_collector/config.py
oidfed_collector/exceptions.py
oidfed_collector/message.py
oidfed_collector/models.py
oidfed_collector/session_manager.py
oidfed_collector/utils.py
oidfed_collector-0.3.1.dist-info/LICENSE
oidfed_collector-0.3.1.dist-info/METADATA
oidfed_collector-0.3.1.dist-info/WHEEL
oidfed_collector-0.3.1.dist-info/entry_points.txt
oidfed_collector-0.3.1.dist-info/RECORD
